README.txt
setup.py
Products/__init__.py
Products.PatchPloneContent.egg-info/PKG-INFO
Products.PatchPloneContent.egg-info/SOURCES.txt
Products.PatchPloneContent.egg-info/dependency_links.txt
Products.PatchPloneContent.egg-info/entry_points.txt
Products.PatchPloneContent.egg-info/namespace_packages.txt
Products.PatchPloneContent.egg-info/not-zip-safe
Products.PatchPloneContent.egg-info/requires.txt
Products.PatchPloneContent.egg-info/top_level.txt
Products/PatchPloneContent/__init__.py
Products/PatchPloneContent/changes.txt
Products/PatchPloneContent/readme.txt
Products/PatchPloneContent/_darcs/format
Products/PatchPloneContent/_darcs/hashed_inventory
Products/PatchPloneContent/_darcs/index_invalid
Products/PatchPloneContent/_darcs/tentative_pristine
Products/PatchPloneContent/_darcs/inventories/0000000186-85d013dabe6e2f91feb8bf5f605c77f726e835c7b3396fd8d012c4a8707fd0ce
Products/PatchPloneContent/_darcs/inventories/0000000408-cb9599788fe216110c6dd007b4eac4578c2307a627da8bb8e568a34a6fa760e2
Products/PatchPloneContent/_darcs/inventories/0000000607-d1dfad610edb89595b361b39e8ba77a3c06eda9fcc2452ac9b4e63a05ae1253c
Products/PatchPloneContent/_darcs/inventories/0000000801-8f2cc3a4899939a912f45f97b09c62e456d9da93eb3154941e170109d0f2b09b
Products/PatchPloneContent/_darcs/inventories/0000000989-882713a70b764c27102ca7715642d7d8b66412c240c7c1482981b4cdf11daf4b
Products/PatchPloneContent/_darcs/inventories/0000001190-ee63862bd967f9177f5f0daede51730c70a95a3a351734d9553a245072a9da86
Products/PatchPloneContent/_darcs/patches/0000000162-bb535e8b6ed299bf1e88ab54928ed68cbb3bd4464625489406e0699e71d99f49
Products/PatchPloneContent/_darcs/patches/0000000165-f5d8409a3825ca1a0cd3d46a5e6ed6274dec2bdbe521432b47b3c0ab323740c2
Products/PatchPloneContent/_darcs/patches/0000000202-3d8d5c18ae70c96790270702682865ca0dd4ea36a14b9c6447291c60b9d9c751
Products/PatchPloneContent/_darcs/patches/0000000699-2e996bcf3cbeb6850d2dc29a1585c57618dffe9ceee853ca1c0433e39e556b60
Products/PatchPloneContent/_darcs/patches/0000000942-dabc47d580440f30efb2d520188719c56bbf383307b1ad879a402a5ebae04361
Products/PatchPloneContent/_darcs/patches/0000001663-efdd214afadd7950c5b3304fe83e9aa10050a66f03efeb0703bbf2c1263a2be4
Products/PatchPloneContent/_darcs/patches/pending
Products/PatchPloneContent/_darcs/patches/pending.tentative
Products/PatchPloneContent/_darcs/prefs/author
Products/PatchPloneContent/_darcs/prefs/binaries
