Metadata-Version: 1.0
Name: Products.PatchPloneContent
Version: 1.0.4
Summary: Various utilities to patch standard Plone content types
Home-page: http://www.nidelven-it.no/d
Author: Morten W. Petersen
Author-email: info@nidelven-it.no
License: GPL
Keywords: python plone archetypes atcontenttypes monkeypatch
Platform: UNKNOWN
Classifier: Programming Language :: Python
Classifier: Framework :: Plone
Classifier: Intended Audience :: Developers
Classifier: Operating System :: OS Independent
Classifier: Topic :: Software Development :: Libraries
